braininvaders2012/__init__.py
braininvaders2012/dataset.py
braininvaders2012/download.py
braininvaders2012-0.1.dist-info/LICENSE
braininvaders2012-0.1.dist-info/METADATA
braininvaders2012-0.1.dist-info/WHEEL
braininvaders2012-0.1.dist-info/top_level.txt
braininvaders2012-0.1.dist-info/RECORD
