Metadata-Version: 2.1
Name: braininvaders2012
Version: 0.1
Summary: Brain Invaders 2012 Dataset
Home-page: https://github.com/plcrodrigues/py.BI.EEG.2012-GIPSA
Author: Pedro Rodrigues
Author-email: pedro.rodrigues01@gmail.com
License: new BSD
Project-URL: Bug Reports, https://github.com/plcrodrigues/py.BI.EEG.2012-GIPSA/issues
Project-URL: Source, https://github.com/plcrodrigues/py.BI.EEG.2012-GIPSA
Keywords: EEG neuroscience signal processing
Platform: UNKNOWN
Classifier: Development Status :: 3 - Alpha
Classifier: Intended Audience :: Science/Research
Classifier: Topic :: Scientific/Engineering
Classifier: License :: OSI Approved
Classifier: Programming Language :: Python :: 3
Classifier: Programming Language :: Python :: 3.4
Classifier: Programming Language :: Python :: 3.5
Classifier: Programming Language :: Python :: 3.6
Classifier: Programming Language :: Python :: 3.7
